setup.py
flask_doclever/flask_doclever.py
flask_doclever.egg-info/PKG-INFO
flask_doclever.egg-info/SOURCES.txt
flask_doclever.egg-info/dependency_links.txt
flask_doclever.egg-info/top_level.txt